agency_swarm/__init__.py
agency_swarm/cli.py
agency_swarm/agency/__init__.py
agency_swarm/agency/agency.py
agency_swarm/agency/genesis/GenesisAgency.py
agency_swarm/agency/genesis/__init__.py
agency_swarm/agency/genesis/util.py
agency_swarm/agency/genesis/AgentCreator/AgentCreator.py
agency_swarm/agency/genesis/AgentCreator/__init__.py
agency_swarm/agency/genesis/GenesisCEO/GenesisCEO.py
agency_swarm/agency/genesis/GenesisCEO/__init__.py
agency_swarm/agency/genesis/OpenAPICreator/OpenAPICreator.py
agency_swarm/agency/genesis/OpenAPICreator/__init__.py
agency_swarm/agency/genesis/ToolCreator/ToolCreator.py
agency_swarm/agency/genesis/ToolCreator/__init__.py
agency_swarm/agents/__init__.py
agency_swarm/agents/agent.py
agency_swarm/agents/BrowsingAgent/BrowsingAgent.py
agency_swarm/agents/BrowsingAgent/__init__.py
agency_swarm/agents/BrowsingAgent/tools/ClickElement.py
agency_swarm/agents/BrowsingAgent/tools/ExportFile.py
agency_swarm/agents/BrowsingAgent/tools/GoBack.py
agency_swarm/agents/BrowsingAgent/tools/ReadURL.py
agency_swarm/agents/BrowsingAgent/tools/Scroll.py
agency_swarm/agents/BrowsingAgent/tools/SelectDropdown.py
agency_swarm/agents/BrowsingAgent/tools/SendKeys.py
agency_swarm/agents/BrowsingAgent/tools/SolveCaptcha.py
agency_swarm/agents/BrowsingAgent/tools/WebPageSummarizer.py
agency_swarm/agents/BrowsingAgent/tools/__init__.py
agency_swarm/agents/BrowsingAgent/tools/util/__init__.py
agency_swarm/agents/BrowsingAgent/tools/util/get_b64_screenshot.py
agency_swarm/agents/BrowsingAgent/tools/util/highlights.py
agency_swarm/agents/BrowsingAgent/tools/util/selenium.py
agency_swarm/agents/Devid/Devid.py
agency_swarm/agents/Devid/__init__.py
agency_swarm/agents/Devid/tools/ChangeFile.py
agency_swarm/agents/Devid/tools/CheckCurrentDir.py
agency_swarm/agents/Devid/tools/CommandExecutor.py
agency_swarm/agents/Devid/tools/DirectoryNavigator.py
agency_swarm/agents/Devid/tools/FileMover.py
agency_swarm/agents/Devid/tools/FileReader.py
agency_skej_framework-0.0.7.dist-info/LICENSE
agency_skej_framework-0.0.7.dist-info/METADATA
agency_skej_framework-0.0.7.dist-info/WHEEL
agency_skej_framework-0.0.7.dist-info/entry_points.txt
agency_skej_framework-0.0.7.dist-info/top_level.txt
agency_skej_framework-0.0.7.dist-info/RECORD
