Metadata-Version: 2.1
Name: agency-skej-framework
Version: 0.0.7
Summary: An open source agent orchestration framework built on top of the latest OpenAI Assistants API.
Home-page: https://skej.com/
Author: priyansh@skej.com
Author-email: priyansh <priyansh@skej.com>
License: MIT License
Project-URL: homepage, https://skej.com
Classifier: Intended Audience :: Developers
Classifier: Topic :: Software Development :: Build Tools
Classifier: License :: OSI Approved :: MIT License
Requires-Python: >=3.7
License-File: LICENSE
Requires-Dist: openai==1.41.0
Requires-Dist: docstring-parser==0.16
Requires-Dist: pydantic==2.8.2
Requires-Dist: datamodel-code-generator==0.25.8
Requires-Dist: deepdiff==6.7.1
Requires-Dist: termcolor==2.4.0
Requires-Dist: python-dotenv==1.0.1
Requires-Dist: rich==13.7.1
Requires-Dist: jsonref==1.1.0
